aptgui/__init__.py
aptgui/__main__.py
aptgui/app.py
aptgui/collections.py
aptgui/layouts/__init__.py
aptgui/layouts/col.py
aptgui/layouts/grid.py
aptgui/layouts/row.py
aptgui/layouts/widgetsequence.py
aptgui/loops/__init__.py
aptgui/loops/asyncio.py
aptgui/loops/tcltk.py
aptgui/mixins/__init__.py
aptgui/mixins/lifecycle.py
aptgui/mixins/repr.py
aptgui/mixins/widget.py
aptgui/options.py
aptgui/py.typed
aptgui/running.py
aptgui/utils.py
aptgui/widgets/__init__.py
aptgui/widgets/button.py
aptgui/widgets/checkbox.py
aptgui/widgets/combobox.py
aptgui/widgets/dropdown.py
aptgui/widgets/fieldset.py
aptgui/widgets/frame.py
aptgui/widgets/label.py
aptgui/widgets/listbox.py
aptgui/widgets/progressbar.py
aptgui/widgets/radiobutton.py
aptgui/widgets/scrollbar.py
aptgui/widgets/sizegrip.py
aptgui/widgets/slider.py
aptgui/widgets/textbox.py
aptgui/window.py
aptgui-1.0.0.dist-info/LICENSE.md
aptgui-1.0.0.dist-info/METADATA
aptgui-1.0.0.dist-info/WHEEL
aptgui-1.0.0.dist-info/RECORD
