Metadata-Version: 2.1
Name: aptgui
Version: 1.0.0
Summary: An Asynchronous Pythonic Tcl/Tk GUI Library
Home-page: https://mawelborn.com
License: MIT
Author: Michael Welborn
Author-email: michael@mawelborn.com
Requires-Python: >=3.10,<4.0
Classifier: License :: OSI Approved :: MIT License
Classifier: Programming Language :: Python :: 3
Classifier: Programming Language :: Python :: 3.10
Classifier: Programming Language :: Python :: 3.11
Classifier: Programming Language :: Python :: 3.12
Project-URL: Repository, https://codeberg.org/mawelborn/aptgui
